bootstrap.py
buildout.cfg
setup.py
twiddler/__init__.py
twiddler/elementtreeplus.py
twiddler/interfaces.py
twiddler/license.txt
twiddler/readme.txt
twiddler/version.txt
twiddler.egg-info/PKG-INFO
twiddler.egg-info/SOURCES.txt
twiddler.egg-info/dependency_links.txt
twiddler.egg-info/not-zip-safe
twiddler.egg-info/requires.txt
twiddler.egg-info/top_level.txt
twiddler/docs/execution.txt
twiddler/docs/filters.txt
twiddler/docs/inandout.txt
twiddler/docs/repeat.txt
twiddler/docs/replace.txt
twiddler/docs/search.txt
twiddler/docs/templating.txt
twiddler/executor/__init__.py
twiddler/executor/source.py
twiddler/executor/source.txt
twiddler/input/__init__.py
twiddler/input/default.py
twiddler/input/default.txt
twiddler/input/filewrapper.py
twiddler/input/filewrapper.txt
twiddler/input/plaintext.py
twiddler/input/plaintext.txt
twiddler/output/MTMultipart.py
twiddler/output/MTText.py
twiddler/output/__init__.py
twiddler/output/default.py
twiddler/output/default.txt
twiddler/output/emailer.py
twiddler/output/emailer.txt
twiddler/tests/__init__.py
twiddler/tests/benchmark1.py
twiddler/tests/benchmark1_twiddler.py
twiddler/tests/benchmark_source.py
twiddler/tests/elementtreeplus.txt
twiddler/tests/searchable.py
twiddler/tests/test.twiddler
twiddler/tests/test_docs.py
twiddler/tests/test_element.py
twiddler/tests/test_elementtreeplus.py
twiddler/tests/test_inputs.py
twiddler/tests/test_nodetree.py
twiddler/tests/test_outputs.py
twiddler/tests/test_repeater.py
twiddler/tests/test_twiddler.py
twiddler/tests/testfile.bin
twiddler/zope2/ZopeTwiddler.py
twiddler/zope2/ZopeTwiddlerCopy.py
twiddler/zope2/ZopeTwiddlerCopyElement.py
twiddler/zope2/ZopeTwiddlerRepeater.py
twiddler/zope2/__init__.py
twiddler/zope2/addTwiddlerForm.twiddler
twiddler/zope2/configure.zcml
twiddler/zope2/configureForm.twiddler
twiddler/zope2/factories.py
twiddler/zope2/interfaces.py
twiddler/zope2/permissions.py
twiddler/zope2/readme.txt
twiddler/zope2/sourceForm.twiddler
twiddler/zope2/twiddler.gif
twiddler/zope2/executor/__init__.py
twiddler/zope2/executor/traverse.py
twiddler/zope2/tests/__init__.py
twiddler/zope2/tests/test_docs.py