Metadata-Version: 1.0
Name: twiddler
Version: 0.9.0
Summary: A simple but flexible templating system for dynamically generating textual output.
Home-page: http://www.simplistix.co.uk/software/python/twiddler
Author: Chris Withers
Author-email: chris@simplistix.co.uk
License: MIT
Keywords: templating
Platform: UNKNOWN
Classifier: Development Status :: 6 - Mature
Classifier: Intended Audience :: Developers
Classifier: License :: OSI Approved :: MIT License
Classifier: Topic :: Text Processing
Classifier: Topic :: Text Processing :: Filters
Classifier: Topic :: Text Processing :: Markup
Classifier: Topic :: Text Processing :: Markup :: HTML
Classifier: Topic :: Text Processing :: Markup :: XML
